gurupy/__init__.py
gurupy/sourcedata.py
gurupy-0.2.dist-info/LICENSE.txt
gurupy-0.2.dist-info/METADATA
gurupy-0.2.dist-info/WHEEL
gurupy-0.2.dist-info/top_level.txt
gurupy-0.2.dist-info/RECORD
