Metadata-Version: 2.1
Name: gurupy
Version: 0.2
Summary: UNKNOWN
Home-page: https://github.com/harveywargo2/guru-wrangler-py
Author: Harvey Wargo
License: UNKNOWN
Keywords: stock financials dividends gurufocus
Platform: UNKNOWN
License-File: LICENSE.txt
Requires-Dist: requests
